{
    "itemGroup.devices_tab_device": "Devices Mod",
    "block.devices.printed_paper": "Defaced Paper",
    "item.devices.ethernet_cable": "Ethernet Cable",
    "item.devices.circuit_board": "Circuit Board",
    "item.devices.motherboard": "Motherboard",
    "item.devices.cpu": "Central Processing Unit",
    "item.devices.hard_drive": "Hard Disk Drive",
    "item.devices.flash_chip": "Flash Chip",
    "item.devices.solid_state_drive": "Solid State Drive",
    "item.devices.ram": "Random Access Memory",
    "item.devices.gpu": "Graphics Processing Unit",
    "item.devices.wifi": "WiFi Module",
    "item.devices.battery": "Battery",
    "item.devices.screen": "Screen",
    "item.devices.controller_unit": "Controller Unit",
    "item.devices.small_electric_motor": "Small Electric Motor",
    "item.devices.carriage": "Carriage",
    "item.devices.plastic_unrefined": "Unrefined Plastic",
    "item.devices.plastic": "Plastic",
    "item.devices.plastic_frame": "Plastic Frame",
    "item.devices.wheel": "Wheel",
    "app.devices.settings": "Settings",
    "app.devices.settings.author": "MrCrayfish",
    "app.devices.app_store": "Application Market",
    "app.devices.app_store.desc": "null",
    "app.devices.app_store.author": "MrCrayfish",
    "app.devices.bank": "Bank",
    "app.devices.bank.desc": "The official bank application for the Device Mod. Allow you to convert emeralds into digital currency.",
    "app.devices.bank.author": "MrCrayfish",
    "app.devices.example": "UI Components",
    "app.devices.example.author": "MrCrayfish",
    "app.devices.file_browser": "File Browser",
    "app.devices.file_browser.author": "MrCrayfish",
    "app.devices.note_stash": "Note Stash",
    "app.devices.note_stash.desc": "The official note application for the Device Mod. Allows you to store simple notes.",
    "app.devices.note_stash.author": "MrCrayfish",
    "app.devices.pixel_painter": "Pixel Painter",
    "app.devices.pixel_painter.author": "MrCrayfish",
    "app.devices.ender_mail": "EnderMail",
    "app.devices.ender_mail.desc": "The official email application for the Device Mod. Allows you to send emails to other players on the server.",
    "app.devices.ender_mail.author": "MrCrayfish",
    "app.devices.boat_racers": "Boat Racers",
    "app.devices.boat_racers.author": "MrCrayfish",
    "app.devices.mine_bay": "MineBay",
    "app.devices.mine_bay.author": "MrCrayfish",
    "message.devices.select_router": "Now select a router to connect this device to.",
    "message.devices.invalid_cable": "Please select a device first before adding it to this router.",
    "message.devices.router_max_devices": "The maximum amount of devices has been reached for this router.",
    "message.devices.device_already_connected": "The selected device is already connected to this router.",
    "message.devices.successful_connection": "Successfully connected the selected device to this router.",
    "message.devices.successful_registered": "Successfully registered the selected device to this router."
}